itglue/__init__.py
itglue/cache.py
itglue/client.py
itglue/config.py
itglue/exceptions.py
itglue/http_client.py
itglue/pagination.py
itglue/version.py
itglue/api/__init__.py
itglue/api/base.py
itglue/api/configurations.py
itglue/api/flexible_assets.py
itglue/api/organizations.py
itglue/api/passwords.py
itglue/api/users.py
itglue/models/__init__.py
itglue/models/base.py
itglue/models/common.py
itglue/models/configuration.py
itglue/models/flexible_asset.py
itglue/models/organization.py
itglue/models/password.py
itglue/models/user.py
py_itglue-0.2.5.dist-info/METADATA
py_itglue-0.2.5.dist-info/WHEEL
py_itglue-0.2.5.dist-info/top_level.txt
py_itglue-0.2.5.dist-info/RECORD
