Metadata-Version: 2.4
Name: py-itglue
Version: 0.2.5
Summary: Comprehensive Python SDK for ITGlue API with AI agent capabilities
Home-page: https://github.com/your-org/py-itglue
Author: Your Organization
Author-email: Your Organization <contact@yourorg.com>
License: MIT
Project-URL: Homepage, https://github.com/yourusername/py-itglue
Project-URL: Repository, https://github.com/yourusername/py-itglue
Project-URL: Documentation, https://github.com/yourusername/py-itglue/blob/main/README.md
Project-URL: Bug Tracker, https://github.com/yourusername/py-itglue/issues
Classifier: Development Status :: 4 - Beta
Classifier: Intended Audience :: Developers
Classifier: License :: OSI Approved :: MIT License
Classifier: Programming Language :: Python :: 3
Classifier: Programming Language :: Python :: 3.10
Classifier: Programming Language :: Python :: 3.11
Classifier: Programming Language :: Python :: 3.12
Requires-Python: >=3.10
Requires-Dist: requests>=2.31.0
Requires-Dist: pydantic>=2.0.0
Requires-Dist: structlog>=23.1.0
Requires-Dist: tenacity>=8.2.0
Requires-Dist: redis>=4.5.0; extra == "redis"
Provides-Extra: dev
Requires-Dist: pytest>=7.0.0; extra == "dev"
Requires-Dist: pytest-cov>=4.0.0; extra == "dev"
Requires-Dist: pytest-mock>=3.10.0; extra == "dev"
Requires-Dist: pytest-asyncio>=0.21.0; extra == "dev"
Requires-Dist: black>=23.0.0; extra == "dev"
Requires-Dist: flake8>=6.0.0; extra == "dev"
Requires-Dist: mypy>=1.0.0; extra == "dev"
Requires-Dist: types-requests>=2.32.0; extra == "dev"
Requires-Dist: pre-commit>=3.0.0; extra == "dev"
Requires-Dist: bandit>=1.7.0; extra == "dev"
Requires-Dist: safety>=2.3.0; extra == "dev"
Provides-Extra: testing
Requires-Dist: pytest>=7.0.0; extra == "testing"
Requires-Dist: pytest-cov>=4.0.0; extra == "testing"
Requires-Dist: pytest-mock>=3.10.0; extra == "testing"
Requires-Dist: pytest-asyncio>=0.21.0; extra == "testing"
Provides-Extra: redis
Requires-Dist: redis>=4.5.0; extra == "redis"
Dynamic: author
Dynamic: home-page
Dynamic: requires-python
